[{"0":"savo-karjala","1":"5345","2":"Albert","3":"Rauli-Jan","4":"Suomen Keskusta","5":"39","6":"M","11":"0","13":"85","14":"http://images.cdn.yle.fi/image/upload/13-1-2658830.jpg","43":"Kyllä","44":"Tyhjä","45":"Ei","46":"Kyllä","47":"Ei"},{"0":"savo-karjala","1":"5359","2":"Antikainen","3":"Sanna","4":"Perussuomalaiset","5":"26","6":"F","11":"0","13":"2","14":"http://images.cdn.yle.fi/image/upload/13-1-2664226.jpg","43":"Kyllä","44":"Kyllä","45":"Ei","46":"Kyllä","47":"Kyllä"},{"0":"savo-karjala","1":"5615","2":"Auvinen","3":"Harri","4":"Vihreä liitto","5":"40","6":"M","11":"0","13":"18","14":"http://images.cdn.yle.fi/image/upload/13-1-2671130.jpg","43":"Ei","44":"Kyllä","45":"Ei","46":"Ei","47":"Kyllä"},{"0":"savo-karjala","1":"5827","2":"Berg-Väänänen","3":"Nelli","4":"Kansallinen Kokoomus","5":"29","6":"F","11":"0","13":"109","14":"http://images.cdn.yle.fi/image/upload/13-1-2658745.jpg","43":"Kyllä","44":"Kyllä","45":"Ei","46":"Ei","47":"Ei"},{"0":"savo-karjala","1":"5322","2":"Bogdanoff","3":"Eero","4":"Perussuomalaiset","5":"59","6":"M","11":"0","13":"3","14":"http://images.cdn.yle.fi/image/upload/13-1-2664158.jpg","43":"Kyllä","44":"Kyllä","45":"Kyllä","46":"Kyllä","47":"Kyllä"},{"0":"savo-karjala","1":"4526","2":"Cederberg","3":"Björn","4":"Suomen Kristillisdemokraatit (KD)","5":"60","6":"M","11":"0","13":"69","14":"http://images.cdn.yle.fi/image/upload/13-1-2659202.jpg","43":"Ei","44":"Kyllä","45":"Kyllä","46":"Ei","47":"Ei"},{"0":"savo-karjala","1":"4375","2":"Dannenberg","3":"Alia","4":"Vasemmistoliitto","5":"40","6":"F","11":"0","13":"125","14":"http://images.cdn.yle.fi/image/upload/13-1-2662713.jpg","43":"Ei","44":"Ei","45":"Ei","46":"Ei","47":"Kyllä"},{"0":"savo-karjala","1":"4564","2":"Eestilä","3":"Markku","4":"Kansallinen Kokoomus","5":"58","6":"M","11":"0","13":"110","14":"http://images.cdn.yle.fi/image/upload/13-1-2658922.jpg","43":"Kyllä","44":"Ei","45":"Ei","46":"Kyllä","47":"Kyllä"},{"0":"savo-karjala","1":"4632","2":"Essayah","3":"Sari","4":"Suomen Kristillisdemokraatit (KD)","5":"48","6":"F","11":"0","13":"70","14":"http://images.cdn.yle.fi/image/upload/13-1-2659086.jpg","43":"Ei","44":"Kyllä","45":"Kyllä","46":"Ei","47":"Ei"},{"0":"savo-karjala","1":"5360","2":"Giray","3":"Ali ","4":"Vihreä liitto","5":"31","6":"M","11":"0","13":"19","14":"http://images.cdn.yle.fi/image/upload/13-1-2671139.jpg","43":"Ei","44":"Kyllä","45":"Ei","46":"Tyhjä","47":"Kyllä"},{"0":"savo-karjala","1":"5844","2":"Gröhn","3":"Marja-Leena ","4":"Perussuomalaiset","5":"50","6":"F","11":"0","13":"4","14":"-","43":"-","44":"Ei","45":"-","46":"-","47":"Kyllä"},{"0":"savo-karjala","1":"5582","2":"Gröhn","3":"Marja-Leena","4":"Perussuomalaiset","5":"50","6":"F","11":"0","13":"4","14":"-","43":"-","44":"-","45":"-","46":"-","47":"-"},{"0":"savo-karjala","1":"4464","2":"Haakana","3":"Marko","4":"Vasemmistoliitto","5":"47","6":"M","11":"0","13":"126","14":"http://images.cdn.yle.fi/image/upload/13-1-2662714.jpg","43":"Ei","44":"Ei","45":"Ei","46":"Ei","47":"Ei"},{"0":"savo-karjala","1":"4396","2":"Hahtala","3":"Mia","4":"Suomen Sosialidemokraattinen Puolue","5":"42","6":"F","11":"0","13":"38","14":"http://images.cdn.yle.fi/image/upload/13-1-2662416.jpg","43":"Ei","44":"Ei","45":"Ei","46":"Kyllä","47":"Kyllä"},{"0":"savo-karjala","1":"6030","2":"Hartikainen","3":"Kari","4":"Vasemmistoliitto","5":"46","6":"M","11":"0","13":"127","14":"http://images.cdn.yle.fi/image/upload/13-1-2662721.jpg","43":"-","44":"-","45":"-","46":"-","47":"-"},{"0":"savo-karjala","1":"5165","2":"Hartikainen","3":"Pentti","4":"Suomen Sosialidemokraattinen Puolue","5":"52","6":"M","11":"0","13":"39","14":"http://images.cdn.yle.fi/image/upload/13-1-2662461.jpg","43":"Kyllä","44":"Ei","45":"Ei","46":"Ei","47":"Kyllä"},{"0":"savo-karjala","1":"4805","2":"Hattunen","3":"Jenna","4":"Kansallinen Kokoomus","5":"24","6":"F","11":"0","13":"111","14":"http://images.cdn.yle.fi/image/upload/13-1-2660420.jpg","43":"Kyllä","44":"Kyllä","45":"Ei","46":"Kyllä","47":"Kyllä"},{"0":"savo-karjala","1":"4655","2":"Haverinen","3":"Timo","4":"Suomen Sosialidemokraattinen Puolue","5":"50","6":"M","11":"0","13":"40","14":"http://images.cdn.yle.fi/image/upload/13-1-2662438.jpg","43":"Kyllä","44":"Ei","45":"Ei","46":"Kyllä","47":"Kyllä"},{"0":"savo-karjala","1":"5091","2":"Heikkinen","3":"Hannakaisa","4":"Suomen Keskusta","5":"40","6":"F","11":"0","13":"86","14":"http://images.cdn.yle.fi/image/upload/13-1-2658845.jpg","43":"Ei","44":"Ei","45":"Ei","46":"Ei","47":"Kyllä"},{"0":"savo-karjala","1":"5003","2":"Help","3":"Anne","4":"Kansallinen Kokoomus","5":"41","6":"F","11":"0","13":"112","14":"http://images.cdn.yle.fi/image/upload/13-1-2660391.jpg","43":"Kyllä","44":"Kyllä","45":"Ei","46":"Kyllä","47":"Kyllä"},{"0":"savo-karjala","1":"4660","2":"Hietanen","3":"Elina","4":"Vihreä liitto","5":"21","6":"F","11":"0","13":"20","14":"http://images.cdn.yle.fi/image/upload/13-1-2664111.jpg","43":"Ei","44":"Ei","45":"Ei","46":"Kyllä","47":"Kyllä"},{"0":"savo-karjala","1":"4311","2":"Hjälm","3":"Heli","4":"Kansallinen Kokoomus","5":"48","6":"F","11":"0","13":"113","14":"http://images.cdn.yle.fi/image/upload/13-1-2660413.jpg","43":"Ei","44":"Kyllä","45":"Ei","46":"Kyllä","47":"Kyllä"},{"0":"savo-karjala","1":"5105","2":"Hoskonen","3":"Hannu","4":"Suomen Keskusta","5":"57","6":"M","11":"0","13":"87","14":"http://images.cdn.yle.fi/image/upload/13-1-2660459.jpg","43":"Kyllä","44":"Ei","45":"-","46":"Ei","47":"Ei"},{"0":"savo-karjala","1":"5604","2":"Huohvanainen","3":"Mari","4":"Suomen Sosialidemokraattinen Puolue","5":"39","6":"F","11":"0","13":"41","14":"http://images.cdn.yle.fi/image/upload/13-1-2662414.jpg","43":"Ei","44":"Ei","45":"Ei","46":"Kyllä","47":"Kyllä"},{"0":"savo-karjala","1":"5092","2":"Huttunen","3":"Hanna","4":"Suomen Keskusta","5":"45","6":"F","11":"0","13":"88","14":"http://images.cdn.yle.fi/image/upload/13-1-2660541.jpg","43":"Ei","44":"-","45":"-","46":"Ei","47":"Kyllä"},{"0":"savo-karjala","1":"4808","2":"Hölttä","3":"Harri","4":"Vihreä liitto","5":"39","6":"M","11":"0","13":"21","14":"http://images.cdn.yle.fi/image/upload/13-1-2664107.jpg","43":"Ei","44":"Ei","45":"Ei","46":"Ei","47":"Ei"},{"0":"savo-karjala","1":"4733","2":"Ikonen","3":"Jaakko Antero","4":"Suomen Sosialidemokraattinen Puolue","5":"32","6":"M","11":"0","13":"42","14":"http://images.cdn.yle.fi/image/upload/13-1-2662466.jpg","43":"Kyllä","44":"Kyllä","45":"Kyllä","46":"Kyllä","47":"Ei"},{"0":"savo-karjala","1":"4402","2":"Ikonen","3":"Päivi","4":"Vihreä liitto","5":"53","6":"F","11":"0","13":"22","14":"http://images.cdn.yle.fi/image/upload/13-1-2664119.jpg","43":"Ei","44":"Ei","45":"Ei","46":"Kyllä","47":"Kyllä"},{"0":"savo-karjala","1":"5229","2":"Jorasmaa","3":"Ilpo","4":"Vihreä liitto","5":"64","6":"M","11":"0","13":"23","14":"http://images.cdn.yle.fi/image/upload/13-1-2671141.jpg","43":"Ei","44":"Ei","45":"Ei","46":"Kyllä","47":"Ei"},{"0":"savo-karjala","1":"4877","2":"Julkunen","3":"Kaarlo","4":"Vasemmistoliitto","5":"60","6":"M","11":"0","13":"128","14":"http://images.cdn.yle.fi/image/upload/13-1-2662887.jpg","43":"Tyhjä","44":"Ei","45":"Ei","46":"Ei","47":"Kyllä"},{"0":"savo-karjala","1":"4432","2":"Järvinen","3":"Anni","4":"Vasemmistoliitto","5":"32","6":"F","11":"0","13":"129","14":"http://images.cdn.yle.fi/image/upload/13-1-2662719.jpg","43":"Ei","44":"Ei","45":"Ei","46":"Kyllä","47":"Kyllä"},{"0":"savo-karjala","1":"4149","2":"Kallioinen","3":"Toni","4":"Suomen Kommunistinen Puolue","5":"27","6":"M","11":"0","13":"60","14":"http://images.cdn.yle.fi/image/upload/13-1-2662486.jpg","43":"Ei","44":"Ei","45":"Ei","46":"Tyhjä","47":"Tyhjä"},{"0":"savo-karjala","1":"5069","2":"Kanniainen","3":"Aino","4":"Suomen Keskusta","5":"53","6":"F","11":"0","13":"89","14":"http://images.cdn.yle.fi/image/upload/13-1-2658788.jpg","43":"Ei","44":"Ei","45":"Kyllä","46":"Ei","47":"Kyllä"},{"0":"savo-karjala","1":"4487","2":"Karjalainen","3":"Sirpa","4":"Vasemmistoliitto","5":"62","6":"F","11":"0","13":"130","14":"http://images.cdn.yle.fi/image/upload/13-1-2662701.jpg","43":"Kyllä","44":"Ei","45":"Ei","46":"Kyllä","47":"Kyllä"},{"0":"savo-karjala","1":"4902","2":"Katainen","3":"Elsi","4":"Suomen Keskusta","5":"48","6":"F","11":"0","13":"90","14":"http://images.cdn.yle.fi/image/upload/13-1-2659022.jpg","43":"Kyllä","44":"Ei","45":"Ei","46":"Ei","47":"Ei"},{"0":"savo-karjala","1":"5125","2":"Kaunisaho","3":"Ari","4":"Perussuomalaiset","5":"40","6":"M","11":"0","13":"5","14":"http://images.cdn.yle.fi/image/upload/13-1-2664264.jpg","43":"Kyllä","44":"Kyllä","45":"Tyhjä","46":"Kyllä","47":"Kyllä"},{"0":"savo-karjala","1":"4579","2":"Kauppinen","3":"Elsi","4":"Vihreä liitto","5":"32","6":"F","11":"0","13":"24","14":"http://images.cdn.yle.fi/image/upload/13-1-2664123.jpg","43":"Ei","44":"Kyllä","45":"Ei","46":"Kyllä","47":"Kyllä"},{"0":"savo-karjala","1":"4513","2":"Keinänen","3":"Tuomo","4":"Suomen Kristillisdemokraatit (KD)","5":"47","6":"M","11":"0","13":"71","14":"http://images.cdn.yle.fi/image/upload/13-1-2659079.jpg","43":"Ei","44":"Ei","45":"Kyllä","46":"Kyllä","47":"Kyllä"},{"0":"savo-karjala","1":"4588","2":"Ketoharju","3":"Hannu","4":"Suomen Kommunistinen Puolue","5":"67","6":"M","11":"0","13":"61","14":"http://images.cdn.yle.fi/image/upload/13-1-2662498.jpg","43":"Ei","44":"Ei","45":"Ei","46":"Ei","47":"Ei"},{"0":"savo-karjala","1":"5148","2":"Kivelä","3":"Antti","4":"Suomen Keskusta","5":"48","6":"M","11":"0","13":"91","14":"http://images.cdn.yle.fi/image/upload/13-1-2658771.jpg","43":"Ei","44":"Kyllä","45":"Ei","46":"Ei","47":"Ei"},{"0":"savo-karjala","1":"4857","2":"Kivelä","3":"Kimmo","4":"Perussuomalaiset","5":"53","6":"M","11":"0","13":"6","14":"http://images.cdn.yle.fi/image/upload/13-1-2669883.jpg","43":"Ei","44":"Ei","45":"Kyllä","46":"Tyhjä","47":"Kyllä"},{"0":"savo-karjala","1":"5294","2":"Kivinen","3":"Kirsti","4":"Suomen Kristillisdemokraatit (KD)","5":"62","6":"F","11":"0","13":"72","14":"http://images.cdn.yle.fi/image/upload/13-1-2661415.jpg","43":"Kyllä","44":"Ei","45":"Kyllä","46":"Ei","47":"Ei"},{"0":"savo-karjala","1":"5234","2":"Kokko","3":"Osmo Urmas","4":"Perussuomalaiset","5":"60","6":"M","11":"0","13":"7","14":"http://images.cdn.yle.fi/image/upload/13-1-2671344.jpg","43":"Ei","44":"Kyllä","45":"Kyllä","46":"Kyllä","47":"Kyllä"},{"0":"savo-karjala","1":"4940","2":"Kolehmainen","3":"Jani","4":"Perussuomalaiset","5":"38","6":"M","11":"0","13":"8","14":"http://images.cdn.yle.fi/image/upload/13-1-2664269.jpg","43":"Kyllä","44":"Kyllä","45":"Ei","46":"Kyllä","47":"Kyllä"},{"0":"savo-karjala","1":"4296","2":"Koljonen","3":"Teuvo","4":"Suomen Kristillisdemokraatit (KD)","5":"68","6":"M","11":"0","13":"73","14":"http://images.cdn.yle.fi/image/upload/13-1-2661412.jpg","43":"Kyllä","44":"Ei","45":"Kyllä","46":"Ei","47":"Ei"},{"0":"savo-karjala","1":"5598","2":"Korhonen","3":"Kaisa","4":"Vasemmistoliitto","5":"49","6":"F","11":"0","13":"131","14":"http://images.cdn.yle.fi/image/upload/13-1-2662753.jpg","43":"Ei","44":"Ei","45":"Ei","46":"Ei","47":"Ei"},{"0":"savo-karjala","1":"6032","2":"Kosunen","3":"Jaakko","4":"Suomen Sosialidemokraattinen Puolue","5":"59","6":"M","11":"0","13":"43","14":"http://images.cdn.yle.fi/image/upload/13-1-2662424.jpg","43":"Ei","44":"Ei","45":"Ei","46":"Ei","47":"Ei"},{"0":"savo-karjala","1":"6031","2":"Kotimäki","3":"Jukka","4":"Suomen Sosialidemokraattinen Puolue","5":"59","6":"M","11":"0","13":"44","14":"http://images.cdn.yle.fi/image/upload/13-1-2662429.jpg","43":"Ei","44":"Ei","45":"Kyllä","46":"Ei","47":"Kyllä"},{"0":"savo-karjala","1":"4456","2":"kuivalainen","3":"ville","4":"Vasemmistoliitto","5":"44","6":"M","11":"0","13":"132","14":"http://images.cdn.yle.fi/image/upload/13-1-2662906.jpg","43":"Kyllä","44":"Kyllä","45":"Kyllä","46":"Kyllä","47":"Kyllä"},{"0":"savo-karjala","1":"4910","2":"Kujanpää","3":"Markku","4":"Suomen Kristillisdemokraatit (KD)","5":"64","6":"M","11":"0","13":"74","14":"http://images.cdn.yle.fi/image/upload/13-1-2660347.jpg","43":"Kyllä","44":"Ei","45":"Kyllä","46":"Ei","47":"Kyllä"},{"0":"savo-karjala","1":"6033","2":"Kukkonen","3":"Arto","4":"Suomen Kristillisdemokraatit (KD)","5":"54","6":"M","11":"0","13":"75","14":"http://images.cdn.yle.fi/image/upload/13-1-2661431.jpg","43":"Ei","44":"Ei","45":"Kyllä","46":"Ei","47":"Kyllä"},{"0":"savo-karjala","1":"5523","2":"Kukkonen","3":"Mikko","4":"Piraattipuolue","5":"33","6":"M","11":"0","13":"34","14":"-","43":"Kyllä","44":"Ei","45":"Ei","46":"Kyllä","47":"Ei"},{"0":"savo-karjala","1":"5230","2":"Kulin","3":"Sirpa","4":"Perussuomalaiset","5":"57","6":"F","11":"0","13":"9","14":"http://images.cdn.yle.fi/image/upload/13-1-2664348.jpg","43":"Ei","44":"Ei","45":"Kyllä","46":"Ei","47":"Kyllä"},{"0":"savo-karjala","1":"6027","2":"Kulmala","3":"Kari","4":"Perussuomalaiset","5":"49","6":"M","11":"0","13":"10","14":"http://images.cdn.yle.fi/image/upload/13-1-2664345.jpg","43":"Kyllä","44":"Ei","45":"Kyllä","46":"Kyllä","47":"Kyllä"},{"0":"savo-karjala","1":"4427","2":"Kultalahti","3":"Reima","4":"Muutos 2011","5":"48","6":"M","11":"0","13":"54","14":"http://images.cdn.yle.fi/image/upload/13-1-2660355.jpg","43":"Ei","44":"Ei","45":"Ei","46":"Kyllä","47":"Kyllä"},{"0":"savo-karjala","1":"4761","2":"Kylänpää","3":"Liisa ","4":"Itsenäisyyspuolue","5":"65","6":"F","11":"0","13":"101","14":"http://images.cdn.yle.fi/image/upload/13-1-2671145.jpg","43":"Ei","44":"Tyhjä","45":"Ei","46":"Kyllä","47":"Kyllä"},{"0":"savo-karjala","1":"4460","2":"Kyyrö","3":"Jarmo","4":"Perussuomalaiset","5":"47","6":"M","11":"0","13":"11","14":"http://images.cdn.yle.fi/image/upload/13-1-2664352.jpg","43":"Kyllä","44":"Ei","45":"Kyllä","46":"Kyllä","47":"Kyllä"},{"0":"savo-karjala","1":"4193","2":"Kähkönen","3":"Päivi","4":"Suomen Kristillisdemokraatit (KD)","5":"52","6":"F","11":"0","13":"76","14":"http://images.cdn.yle.fi/image/upload/13-1-2659185.jpg","43":"Ei","44":"Ei","45":"Kyllä","46":"Ei","47":"Kyllä"},{"0":"savo-karjala","1":"5248","2":"Kääriäinen","3":"Seppo","4":"Suomen Keskusta","5":"67","6":"M","11":"0","13":"92","14":"http://images.cdn.yle.fi/image/upload/13-1-2659042.jpg","43":"Ei","44":"Ei","45":"Ei","46":"Ei","47":"Ei"},{"0":"savo-karjala","1":"5634","2":"Laurinkari","3":"Juhani","4":"Suomen Kristillisdemokraatit (KD)","5":"68","6":"M","11":"1","13":"77","14":"http://images.cdn.yle.fi/image/upload/13-1-2660882.jpg","43":"Tyhjä","44":"Ei","45":"Tyhjä","46":"Ei","47":"Ei"},{"0":"savo-karjala","1":"4649","2":"Lintunen","3":"Rauno","4":"Kommunistinen Työväenpuolue - Rauhan ja Sosialismin puolesta","5":"66","6":"M","11":"0","13":"68","14":"-","43":"Ei","44":"Ei","45":"Tyhjä","46":"Ei","47":"Kyllä"},{"0":"savo-karjala","1":"6361","2":"Lipponen","3":"Arto","4":"Suomen Työväenpuolue STP","5":"71","6":"M","11":"0","13":"57","14":"-","43":"-","44":"-","45":"-","46":"-","47":"-"},{"0":"savo-karjala","1":"5462","2":"Loimalahti","3":"Antti","4":"Vihreä liitto","5":"45","6":"M","11":"0","13":"25","14":"http://images.cdn.yle.fi/image/upload/13-1-2671133.jpg","43":"Ei","44":"Ei","45":"Ei","46":"Ei","47":"Kyllä"},{"0":"savo-karjala","1":"5097","2":"Maksniemi","3":"Marianne","4":"Suomen Kommunistinen Puolue","5":"28","6":"F","11":"0","13":"62","14":"http://images.cdn.yle.fi/image/upload/13-1-2700548.jpg","43":"Ei","44":"Ei","45":"Ei","46":"Ei","47":"Ei"},{"0":"savo-karjala","1":"4392","2":"Mannelin","3":"Maarita","4":"Kansallinen Kokoomus","5":"47","6":"F","11":"0","13":"114","14":"http://images.cdn.yle.fi/image/upload/13-1-2660414.jpg","43":"Kyllä","44":"Kyllä","45":"Ei","46":"Kyllä","47":"Kyllä"},{"0":"savo-karjala","1":"4476","2":"Marjeta","3":"Ari","4":"Suomen Sosialidemokraattinen Puolue","5":"55","6":"M","11":"0","13":"45","14":"http://images.cdn.yle.fi/image/upload/13-1-2662456.jpg","43":"Ei","44":"Ei","45":"Ei","46":"Ei","47":"Ei"},{"0":"savo-karjala","1":"5654","2":"Markkanen","3":"Sallamaarit","4":"Suomen Keskusta","5":"26","6":"F","11":"0","13":"93","14":"http://images.cdn.yle.fi/image/upload/13-1-2658796.jpg","43":"Kyllä","44":"Kyllä","45":"Ei","46":"Kyllä","47":"Ei"},{"0":"savo-karjala","1":"4462","2":"Martiskin","3":"Jouni","4":"Suomen Sosialidemokraattinen Puolue","5":"49","6":"M","11":"0","13":"46","14":"http://images.cdn.yle.fi/image/upload/13-1-2662444.jpg","43":"Kyllä","44":"Ei","45":"Ei","46":"Kyllä","47":"Kyllä"},{"0":"savo-karjala","1":"5216","2":"Matikainen","3":"Matti","4":"Vasemmistoliitto","5":"68","6":"M","11":"0","13":"133","14":"http://images.cdn.yle.fi/image/upload/13-1-2662750.jpg","43":"Ei","44":"Ei","45":"Ei","46":"Kyllä","47":"Ei"},{"0":"savo-karjala","1":"5432","2":"Mikkonen ","3":"Jussi","4":"Suomen Kristillisdemokraatit (KD)","5":"20","6":"M","11":"0","13":"78","14":"http://images.cdn.yle.fi/image/upload/13-1-2660335.jpg","43":"Ei","44":"Kyllä","45":"Ei","46":"Ei","47":"Ei"},{"0":"savo-karjala","1":"5392","2":"Mikkonen","3":"Krista","4":"Vihreä liitto","5":"42","6":"F","11":"0","13":"26","14":"http://images.cdn.yle.fi/image/upload/13-1-2664127.jpg","43":"Ei","44":"Ei","45":"Ei","46":"Kyllä","47":"Ei"},{"0":"savo-karjala","1":"4729","2":"Mikkonen","3":"Marjaana","4":"Perussuomalaiset","5":"44","6":"F","11":"0","13":"12","14":"http://images.cdn.yle.fi/image/upload/13-1-2664353.jpg","43":"Ei","44":"Ei","45":"Tyhjä","46":"Kyllä","47":"Kyllä"},{"0":"savo-karjala","1":"6200","2":"Montonen","3":"Petri","4":"Itsenäisyyspuolue","5":"45","6":"M","11":"0","13":"106","14":"-","43":"Ei","44":"Ei","45":"Kyllä","46":"Kyllä","47":"Kyllä"},{"0":"savo-karjala","1":"4319","2":"Musikka","3":"Sinikka","4":"Suomen Keskusta","5":"55","6":"F","11":"0","13":"94","14":"http://images.cdn.yle.fi/image/upload/13-1-2658808.jpg","43":"Kyllä","44":"Kyllä","45":"Ei","46":"Kyllä","47":"Kyllä"},{"0":"savo-karjala","1":"6363","2":"Mustonen","3":"Eeva","4":"Suomen Kommunistinen Puolue","5":"69","6":"F","11":"0","13":"63","14":"-","43":"-","44":"-","45":"-","46":"-","47":"-"},{"0":"savo-karjala","1":"6040","2":"Mustonen","3":"Juha","4":"Suomen Keskusta","5":"57","6":"M","11":"0","13":"95","14":"http://images.cdn.yle.fi/image/upload/13-1-2658823.jpg","43":"Ei","44":"Kyllä","45":"Ei","46":"Ei","47":"Kyllä"},{"0":"savo-karjala","1":"5035","2":"Mustonen","3":"Pekka","4":"Piraattipuolue","5":"33","6":"M","11":"0","13":"35","14":"-","43":"Kyllä","44":"Ei","45":"Ei","46":"Kyllä","47":"Kyllä"},{"0":"savo-karjala","1":"5123","2":"Mutanen","3":"Miika","4":"Kansallinen Kokoomus","5":"35","6":"M","11":"0","13":"115","14":"http://images.cdn.yle.fi/image/upload/13-1-2660436.jpg","43":"Kyllä","44":"Kyllä","45":"Ei","46":"Kyllä","47":"Kyllä"},{"0":"savo-karjala","1":"4286","2":"Myller","3":"Riitta","4":"Suomen Sosialidemokraattinen Puolue","5":"58","6":"F","11":"0","13":"47","14":"http://images.cdn.yle.fi/image/upload/13-1-2659169.jpg","43":"Ei","44":"Ei","45":"Ei","46":"Ei","47":"Ei"},{"0":"savo-karjala","1":"4829","2":"Mäkisalo-Ropponen","3":"Merja","4":"Suomen Sosialidemokraattinen Puolue","5":"56","6":"F","11":"0","13":"48","14":"http://images.cdn.yle.fi/image/upload/13-1-2659115.jpg","43":"Ei","44":"Ei","45":"Ei","46":"Ei","47":"Ei"},{"0":"savo-karjala","1":"4871","2":"Määttä","3":"Henry","4":"Suomen Kristillisdemokraatit (KD)","5":"35","6":"M","11":"0","13":"79","14":"http://images.cdn.yle.fi/image/upload/13-1-2659190.jpg","43":"Ei","44":"Kyllä","45":"Kyllä","46":"Ei","47":"Kyllä"},{"0":"savo-karjala","1":"4304","2":"Niiranen","3":"Pekka","4":"Kansallinen Kokoomus","5":"51","6":"M","11":"0","13":"116","14":"http://images.cdn.yle.fi/image/upload/13-1-2684124.jpg","43":"Kyllä","44":"Kyllä","45":"Kyllä","46":"Kyllä","47":"Kyllä"},{"0":"savo-karjala","1":"4353","2":"Nyman","3":"Ako","4":"Suomen Kommunistinen Puolue","5":"25","6":"M","11":"0","13":"64","14":"http://images.cdn.yle.fi/image/upload/13-1-2664493.jpg","43":"Ei","44":"Ei","45":"Ei","46":"Kyllä","47":"Kyllä"},{"0":"savo-karjala","1":"4492","2":"Oinonen","3":"Pentti","4":"Perussuomalaiset","5":"62","6":"M","11":"0","13":"13","14":"-","43":"Ei","44":"Ei","45":"Kyllä","46":"Kyllä","47":"Kyllä"},{"0":"savo-karjala","1":"6036","2":"Oksman","3":"Merja","4":"Kansallinen Kokoomus","5":"58","6":"F","11":"0","13":"117","14":"http://images.cdn.yle.fi/image/upload/13-1-2660389.jpg","43":"-","44":"-","45":"-","46":"-","47":"-"},{"0":"savo-karjala","1":"4953","2":"Olkkonen","3":"Anna","4":"Suomen Keskusta","5":"55","6":"F","11":"0","13":"96","14":"http://images.cdn.yle.fi/image/upload/13-1-2658770.jpg","43":"Ei","44":"Kyllä","45":"Ei","46":"Kyllä","47":"Ei"},{"0":"savo-karjala","1":"4260","2":"Orava","3":"Joni","4":"Vasemmistoliitto","5":"37","6":"M","11":"0","13":"134","14":"http://images.cdn.yle.fi/image/upload/13-1-2662779.jpg","43":"Ei","44":"Ei","45":"Ei","46":"Ei","47":"Ei"},{"0":"savo-karjala","1":"5613","2":"Paananen","3":"Pasi","4":"Perussuomalaiset","5":"49","6":"M","11":"0","13":"14","14":"http://images.cdn.yle.fi/image/upload/13-1-2664387.jpg","43":"Kyllä","44":"Ei","45":"Kyllä","46":"Kyllä","47":"Kyllä"},{"0":"savo-karjala","1":"4551","2":"Pahajoki","3":"Juho","4":"Suomen Keskusta","5":"32","6":"M","11":"0","13":"97","14":"http://images.cdn.yle.fi/image/upload/13-1-2658787.jpg","43":"Kyllä","44":"Kyllä","45":"Ei","46":"Kyllä","47":"Kyllä"},{"0":"savo-karjala","1":"6362","2":"Parviainen","3":"Juha","4":"Suomen Työväenpuolue STP","5":"50","6":"M","11":"0","13":"58","14":"-","43":"-","44":"-","45":"-","46":"-","47":"-"},{"0":"savo-karjala","1":"4837","2":"Paulo-Tuovinen","3":"Anne","4":"Vihreä liitto","5":"54","6":"F","11":"0","13":"27","14":"http://images.cdn.yle.fi/image/upload/13-1-2664100.jpg","43":"Ei","44":"Ei","45":"Ei","46":"Ei","47":"Tyhjä"},{"0":"savo-karjala","1":"5546","2":"Pekkala","3":"Janne","4":"Vihreä liitto","5":"29","6":"M","11":"0","13":"28","14":"-","43":"Ei","44":"Kyllä","45":"Ei","46":"Kyllä","47":"Kyllä"},{"0":"savo-karjala","1":"5530","2":"Pietarinen","3":"Mikko","4":"Piraattipuolue","5":"22","6":"M","11":"0","13":"36","14":"-","43":"Kyllä","44":"Kyllä","45":"Ei","46":"Kyllä","47":"Kyllä"},{"0":"savo-karjala","1":"4924","2":"Pietikäinen","3":"Liisa","4":"Vihreä liitto","5":"38","6":"F","11":"0","13":"29","14":"http://images.cdn.yle.fi/image/upload/13-1-2664206.jpg","43":"Ei","44":"Ei","45":"Ei","46":"Ei","47":"Ei"},{"0":"savo-karjala","1":"6028","2":"Pikkarainen","3":"Rauno","4":"Vasemmistoliitto","5":"49","6":"M","11":"0","13":"135","14":"http://images.cdn.yle.fi/image/upload/13-1-2662917.jpg","43":"Kyllä","44":"Ei","45":"Ei","46":"Kyllä","47":"Kyllä"},{"0":"savo-karjala","1":"5595","2":"Pippola","3":"Jarmo","4":"Suomen Kristillisdemokraatit (KD)","5":"55","6":"M","11":"0","13":"80","14":"http://images.cdn.yle.fi/image/upload/13-1-2700480.jpg","43":"Tyhjä","44":"Kyllä","45":"Kyllä","46":"Ei","47":"Ei"},{"0":"savo-karjala","1":"6029","2":"Puurunen","3":"Kirsti","4":"Vasemmistoliitto","5":"60","6":"F","11":"0","13":"136","14":"http://images.cdn.yle.fi/image/upload/13-1-2662865.jpg","43":"Ei","44":"Ei","45":"Ei","46":"Kyllä","47":"Kyllä"},{"0":"savo-karjala","1":"5812","2":"Pääkkö","3":"Sakari","4":"Kansallinen Kokoomus","5":"20","6":"M","11":"0","13":"118","14":"http://images.cdn.yle.fi/image/upload/13-1-2658742.jpg","43":"Kyllä","44":"Kyllä","45":"Ei","46":"Ei","47":"Ei"},{"0":"savo-karjala","1":"5184","2":"Raassina","3":"Sari","4":"Kansallinen Kokoomus","5":"51","6":"F","11":"0","13":"119","14":"http://images.cdn.yle.fi/image/upload/13-1-2658748.jpg","43":"Kyllä","44":"Kyllä","45":"Ei","46":"Ei","47":"Ei"},{"0":"savo-karjala","1":"5267","2":"Rantonen","3":"Ossi","4":"Itsenäisyyspuolue","5":"52","6":"M","11":"1","13":"105","14":"http://images.cdn.yle.fi/image/upload/13-1-2700537.jpg","43":"Kyllä","44":"Ei","45":"Kyllä","46":"Kyllä","47":"Kyllä"},{"0":"savo-karjala","1":"5049","2":"Rautavuori","3":"Armi","4":"Suomen Sosialidemokraattinen Puolue","5":"59","6":"F","11":"0","13":"49","14":"http://images.cdn.yle.fi/image/upload/13-1-2662469.jpg","43":"Ei","44":"Ei","45":"Ei","46":"Kyllä","47":"Ei"},{"0":"savo-karjala","1":"5010","2":"Ravi","3":"Pekka","4":"Kansallinen Kokoomus","5":"65","6":"M","11":"0","13":"120","14":"http://images.cdn.yle.fi/image/upload/13-1-2659090.jpg","43":"Kyllä","44":"Kyllä","45":"-","46":"Ei","47":"Ei"},{"0":"savo-karjala","1":"5242","2":"Reijonen","3":"Eero","4":"Suomen Keskusta","5":"67","6":"M","11":"0","13":"98","14":"http://images.cdn.yle.fi/image/upload/13-1-2671366.jpg","43":"Ei","44":"Ei","45":"Kyllä","46":"Kyllä","47":"Kyllä"},{"0":"savo-karjala","1":"5500","2":"Reijonen","3":"Minna","4":"Perussuomalaiset","5":"42","6":"F","11":"0","13":"15","14":"http://images.cdn.yle.fi/image/upload/13-1-2664381.jpg","43":"Ei","44":"Ei","45":"Kyllä","46":"Kyllä","47":"Kyllä"},{"0":"savo-karjala","1":"4816","2":"Repo","3":"Timo","4":"Itsenäisyyspuolue","5":"27","6":"M","11":"0","13":"104","14":"http://images.cdn.yle.fi/image/upload/13-1-2669529.jpg","43":"Ei","44":"Ei","45":"Ei","46":"Ei","47":"Kyllä"},{"0":"savo-karjala","1":"4421","2":"Reponen","3":"Eveliina","4":"Suomen Sosialidemokraattinen Puolue","5":"26","6":"F","11":"0","13":"50","14":"http://images.cdn.yle.fi/image/upload/13-1-2662479.jpg","43":"Ei","44":"Ei","45":"Ei","46":"Kyllä","47":"Ei"},{"0":"savo-karjala","1":"5046","2":"Rissanen","3":"Susanna","4":"Suomen Kommunistinen Puolue","5":"30","6":"F","11":"0","13":"65","14":"http://images.cdn.yle.fi/image/upload/13-1-2664486.jpg","43":"Ei","44":"Ei","45":"Ei","46":"Kyllä","47":"Ei"},{"0":"savo-karjala","1":"4853","2":"Roponen","3":"Anne","4":"Vihreä liitto","5":"52","6":"F","11":"0","13":"30","14":"http://images.cdn.yle.fi/image/upload/13-1-2664216.jpg","43":"Ei","44":"Ei","45":"Ei","46":"Ei","47":"Kyllä"},{"0":"savo-karjala","1":"5329","2":"Rossi","3":"Markku","4":"Suomen Keskusta","5":"59","6":"M","11":"0","13":"99","14":"http://images.cdn.yle.fi/image/upload/13-1-2659039.jpg","43":"Kyllä","44":"Kyllä","45":"Ei","46":"Ei","47":"Kyllä"},{"0":"savo-karjala","1":"6034","2":"Rothström","3":"Markko","4":"Kansallinen Kokoomus","5":"47","6":"M","11":"0","13":"121","14":"http://images.cdn.yle.fi/image/upload/13-1-2660737.jpg","43":"Kyllä","44":"Kyllä","45":"Ei","46":"Kyllä","47":"Kyllä"},{"0":"savo-karjala","1":"4436","2":"Ruuskanen","3":"Anne","4":"Suomen Kommunistinen Puolue","5":"54","6":"F","11":"0","13":"66","14":"http://images.cdn.yle.fi/image/upload/13-1-2700542.jpg","43":"Ei","44":"Ei","45":"Ei","46":"Kyllä","47":"Kyllä"},{"0":"savo-karjala","1":"4604","2":"Ruuskanen","3":"Mauno","4":"Itsenäisyyspuolue","5":"67","6":"M","11":"0","13":"107","14":"-","43":"Ei","44":"Ei","45":"Kyllä","46":"Ei","47":"Kyllä"},{"0":"savo-karjala","1":"4746","2":"Räsänen","3":"Sami","4":"Suomen Kristillisdemokraatit (KD)","5":"39","6":"M","11":"0","13":"81","14":"http://images.cdn.yle.fi/image/upload/13-1-2659198.jpg","43":"Ei","44":"Kyllä","45":"Kyllä","46":"Kyllä","47":"Ei"},{"0":"savo-karjala","1":"4711","2":"Saarelainen","3":"Antti","4":"Vasemmistoliitto","5":"25","6":"M","11":"0","13":"137","14":"http://images.cdn.yle.fi/image/upload/13-1-2662843.jpg","43":"Ei","44":"Ei","45":"Ei","46":"Kyllä","47":"Kyllä"},{"0":"savo-karjala","1":"5208","2":"Saastamoinen","3":"Esko Juhani","4":"Perussuomalaiset","5":"55","6":"M","11":"0","13":"16","14":"-","43":"Ei","44":"Kyllä","45":"Kyllä","46":"Kyllä","47":"Kyllä"},{"0":"savo-karjala","1":"5352","2":"Saikkonen","3":"Lasse","4":"Piraattipuolue","5":"48","6":"M","11":"0","13":"37","14":"-","43":"Kyllä","44":"Ei","45":"Ei","46":"Kyllä","47":"Kyllä"},{"0":"savo-karjala","1":"4639","2":"Sarisalmi","3":"Joona","4":"Itsenäisyyspuolue","5":"32","6":"M","11":"1","13":"102","14":"http://images.cdn.yle.fi/image/upload/13-1-2661409.jpg","43":"Ei","44":"Ei","45":"Ei","46":"Ei","47":"Kyllä"},{"0":"savo-karjala","1":"6035","2":"Savolainen","3":"Jukka","4":"Kansallinen Kokoomus","5":"49","6":"M","11":"0","13":"122","14":"http://images.cdn.yle.fi/image/upload/13-1-2660542.jpg","43":"Kyllä","44":"Kyllä","45":"Ei","46":"Kyllä","47":"Kyllä"},{"0":"savo-karjala","1":"4784","2":"Semi","3":"Matti","4":"Vasemmistoliitto","5":"58","6":"M","11":"0","13":"138","14":"http://images.cdn.yle.fi/image/upload/13-1-2662879.jpg","43":"Tyhjä","44":"Ei","45":"Ei","46":"Kyllä","47":"Kyllä"},{"0":"savo-karjala","1":"4653","2":"Seppänen","3":"Eero","4":"Itsenäisyyspuolue","5":"65","6":"M","11":"0","13":"108","14":"http://images.cdn.yle.fi/image/upload/13-1-2661185.jpg","43":"Ei","44":"Kyllä","45":"Kyllä","46":"Ei","47":"Kyllä"},{"0":"savo-karjala","1":"4944","2":"Sihvonen","3":"Aulikki","4":"Kansallinen Kokoomus","5":"51","6":"F","11":"0","13":"123","14":"http://images.cdn.yle.fi/image/upload/13-1-2660717.jpg","43":"Kyllä","44":"Ei","45":"Ei","46":"Ei","47":"Kyllä"},{"0":"savo-karjala","1":"4628","2":"Silvennoinen","3":"Maija","4":"Suomen Kristillisdemokraatit (KD)","5":"36","6":"F","11":"0","13":"82","14":"http://images.cdn.yle.fi/image/upload/13-1-2659189.jpg","43":"Kyllä","44":"Ei","45":"Kyllä","46":"Ei","47":"Kyllä"},{"0":"savo-karjala","1":"4257","2":"Suhonen","3":"Timo","4":"Suomen Sosialidemokraattinen Puolue","5":"40","6":"M","11":"0","13":"51","14":"http://images.cdn.yle.fi/image/upload/13-1-2662499.jpg","43":"Kyllä","44":"Ei","45":"Ei","46":"Kyllä","47":"Kyllä"},{"0":"savo-karjala","1":"6235","2":"Suikkanen","3":"Sirpa","4":"Suomen Kristillisdemokraatit (KD)","5":"51","6":"F","11":"0","13":"83","14":"-","43":"Ei","44":"Ei","45":"Kyllä","46":"Ei","47":"Ei"},{"0":"savo-karjala","1":"4973","2":"Tahvanainen","3":"Petteri","4":"Vasemmistoliitto","5":"47","6":"M","11":"0","13":"139","14":"http://images.cdn.yle.fi/image/upload/13-1-2662896.jpg","43":"Kyllä","44":"Ei","45":"Ei","46":"Kyllä","47":"Kyllä"},{"0":"savo-karjala","1":"5552","2":"Taivassalo","3":"Milka","4":"Suomen Kristillisdemokraatit (KD)","5":"28","6":"F","11":"0","13":"84","14":"-","43":"Ei","44":"Ei","45":"Tyhjä","46":"Ei","47":"Ei"},{"0":"savo-karjala","1":"5568","2":"Tamio","3":"Kim","4":"Vihreä liitto","5":"25","6":"M","11":"0","13":"31","14":"http://images.cdn.yle.fi/image/upload/13-1-2671119.jpg","43":"Ei","44":"Ei","45":"Ei","46":"Kyllä","47":"Kyllä"},{"0":"savo-karjala","1":"6041","2":"Tanski","3":"Juhani ","4":"Suomen Työväenpuolue STP","5":"68","6":"M","11":"0","13":"59","14":"http://images.cdn.yle.fi/image/upload/13-1-2700545.jpg","43":"Ei","44":"Ei","45":"Ei","46":"Kyllä","47":"Ei"},{"0":"savo-karjala","1":"6037","2":"Tolvanen","3":"Pentti","4":"Itsenäisyyspuolue","5":"66","6":"M","11":"0","13":"103","14":"http://images.cdn.yle.fi/image/upload/13-1-2660370.jpg","43":"Kyllä","44":"Kyllä","45":"Tyhjä","46":"Kyllä","47":"Kyllä"},{"0":"savo-karjala","1":"5373","2":"turpeinen","3":"tero","4":"Muutos 2011","5":"27","6":"M","11":"0","13":"55","14":"-","43":"Kyllä","44":"Kyllä","45":"Kyllä","46":"Kyllä","47":"Kyllä"},{"0":"savo-karjala","1":"4425","2":"Törmälä","3":"Anssi","4":"Kansallinen Kokoomus","5":"35","6":"M","11":"0","13":"124","14":"http://images.cdn.yle.fi/image/upload/13-1-2660702.jpg","43":"Kyllä","44":"Kyllä","45":"Ei","46":"Kyllä","47":"Ei"},{"0":"savo-karjala","1":"5151","2":"Vaskonen","3":"Martti","4":"Suomen Kommunistinen Puolue","5":"60","6":"M","11":"0","13":"67","14":"http://images.cdn.yle.fi/image/upload/13-1-2662496.jpg","43":"Ei","44":"Ei","45":"Ei","46":"Ei","47":"Kyllä"},{"0":"savo-karjala","1":"5031","2":"Vauhkonen","3":"Jouni","4":"Vihreä liitto","5":"56","6":"M","11":"0","13":"32","14":"http://images.cdn.yle.fi/image/upload/13-1-2653990.jpg","43":"Ei","44":"Ei","45":"Ei","46":"Ei","47":"Ei"},{"0":"savo-karjala","1":"4230","2":"Vehviläinen","3":"Anu","4":"Suomen Keskusta","5":"51","6":"F","11":"0","13":"100","14":"http://images.cdn.yle.fi/image/upload/13-1-2659023.jpg","43":"Ei","44":"Ei","45":"Ei","46":"Ei","47":"Ei"},{"0":"savo-karjala","1":"6038","2":"Vänskä","3":"Jorma","4":"Muutos 2011","5":"68","6":"M","11":"0","13":"56","14":"http://images.cdn.yle.fi/image/upload/13-1-2660358.jpg","43":"-","44":"-","45":"-","46":"-","47":"-"},{"0":"savo-karjala","1":"5709","2":"Väyrynen","3":"Ritva","4":"Vasemmistoliitto","5":"46","6":"F","11":"0","13":"140","14":"http://images.cdn.yle.fi/image/upload/13-1-2662910.jpg","43":"Ei","44":"Ei","45":"Ei","46":"Kyllä","47":"Ei"},{"0":"savo-karjala","1":"4450","2":"Väätäinen","3":"Tuula","4":"Suomen Sosialidemokraattinen Puolue","5":"59","6":"F","11":"0","13":"52","14":"http://images.cdn.yle.fi/image/upload/13-1-2658842.jpg","43":"Ei","44":"Ei","45":"Ei","46":"Ei","47":"Ei"},{"0":"savo-karjala","1":"4201","2":"Wihonen","3":"Jussi","4":"Perussuomalaiset","5":"51","6":"M","11":"0","13":"17","14":"http://images.cdn.yle.fi/image/upload/13-1-2664389.jpg","43":"Kyllä","44":"Ei","45":"Ei","46":"Kyllä","47":"Kyllä"},{"0":"savo-karjala","1":"4687","2":"Willman","3":"Veera","4":"Vihreä liitto","5":"26","6":"F","11":"0","13":"33","14":"http://images.cdn.yle.fi/image/upload/13-1-2664220.jpg","43":"Ei","44":"Ei","45":"Ei","46":"Kyllä","47":"Ei"},{"0":"savo-karjala","1":"4404","2":"Åhman-Kuosmanen","3":"Kati","4":"Suomen Sosialidemokraattinen Puolue","5":"46","6":"F","11":"0","13":"53","14":"http://images.cdn.yle.fi/image/upload/13-1-2662585.jpg","43":"Kyllä","44":"Ei","45":"Ei","46":"Kyllä","47":"Kyllä"}]